cacholote/__init__.py
cacholote/alembic.ini
cacholote/alembic_cli.py
cacholote/cache.py
cacholote/clean.py
cacholote/config.py
cacholote/database.py
cacholote/decode.py
cacholote/encode.py
cacholote/extra_encoders.py
cacholote/py.typed
cacholote/utils.py
cacholote/version.py
cacholote/alembic/README
cacholote/alembic/env.py
cacholote/alembic/script.py.mako
cacholote/alembic/versions/a38663d192e5_add_created_at_and_rename_timestamp_.py
cacholote/alembic/versions/fac14caeb10d_adding_index_key_expiration.py
cacholote-1.7.1.dist-info/licenses/LICENSE
cacholote-1.7.1.dist-info/METADATA
cacholote-1.7.1.dist-info/WHEEL
cacholote-1.7.1.dist-info/entry_points.txt
cacholote-1.7.1.dist-info/top_level.txt
cacholote-1.7.1.dist-info/RECORD
