Metadata-Version: 2.4
Name: cacholote
Version: 1.7.1
Summary: Efficiently cache calls to functions
License:                                  Apache License
Classifier: Development Status :: 2 - Pre-Alpha
Classifier: Intended Audience :: Science/Research
Classifier: License :: OSI Approved :: Apache Software License
Classifier: Operating System :: OS Independent
Classifier: Programming Language :: Python
Classifier: Programming Language :: Python :: 3
Classifier: Programming Language :: Python :: 3.9
Classifier: Programming Language :: Python :: 3.10
Classifier: Programming Language :: Python :: 3.11
Classifier: Programming Language :: Python :: 3.12
Classifier: Topic :: Scientific/Engineering
License-File: LICENSE
Requires-Dist: alembic
Requires-Dist: fsspec
Requires-Dist: pydantic
Requires-Dist: pydantic-settings
Requires-Dist: sqlalchemy>=2.0.9
Requires-Dist: sqlalchemy_utils
Requires-Dist: structlog
Dynamic: license-file
